rtcbot/__init__.py
rtcbot/arduino.py
rtcbot/audio.py
rtcbot/camera.py
rtcbot/connection.py
rtcbot/inputs.py
rtcbot/javascript.py
rtcbot/rtcbot.js
rtcbot/subscriptions.py
rtcbot/tracks.py
rtcbot/websocket.py
rtcbot/base/__init__.py
rtcbot/base/base.py
rtcbot/base/events.py
rtcbot/base/multiprocess.py
rtcbot/base/thread.py
rtcbot/devices/__init__.py
rtcbot/devices/gps.py
tests/__init__.py
tests/test_RTCConnection.py
tests/test_base.py
tests/test_subscriptions.py
tests/test_websocket.py
rtcbot-0.2.5.dist-info/LICENSE.txt
rtcbot-0.2.5.dist-info/METADATA
rtcbot-0.2.5.dist-info/WHEEL
rtcbot-0.2.5.dist-info/top_level.txt
rtcbot-0.2.5.dist-info/RECORD
