Metadata-Version: 2.1
Name: rtcbot
Version: 0.2.5
Summary: An asyncio-focused library for webrtc robot control
Home-page: https://github.com/dkumor/rtcbot
Author: Daniel Kumor
Author-email: pypi@dkumor.com
License: MIT
Classifier: Intended Audience :: Developers
Classifier: Intended Audience :: Science/Research
Classifier: License :: OSI Approved :: MIT License
Classifier: Programming Language :: Python :: 3
Classifier: Programming Language :: Python :: 3.7
Requires-Python: >=3.7.0
License-File: LICENSE.txt
Requires-Dist: aiortc
Requires-Dist: pyserial
Requires-Dist: pyserial-asyncio
Requires-Dist: numpy
Requires-Dist: aiohttp
Requires-Dist: SoundCard
Requires-Dist: inputs
Requires-Dist: pynmea2
